pythonbible/__init__.py
pythonbible/bible/__init__.py
pythonbible/bible/bible.py
pythonbible/bible/errors.py
pythonbible/book_groups.py
pythonbible/books/__init__.py
pythonbible/books/common_constants.py
pythonbible/books/john.py
pythonbible/converter.py
pythonbible/counters/__init__.py
pythonbible/counters/book_counter.py
pythonbible/counters/chapter_counter.py
pythonbible/counters/verse_counter.py
pythonbible/errors.py
pythonbible/formatter.py
pythonbible/normalized_reference.py
pythonbible/parser.py
pythonbible/regular_expressions.py
pythonbible/roman_numeral_util.py
pythonbible/validator.py
pythonbible/verses.py
pythonbible/versions.py
pythonbible-0.15.5.dist-info/WHEEL
pythonbible-0.15.5.dist-info/METADATA
pythonbible-0.15.5.dist-info/RECORD
