Metadata-Version: 2.4
Name: pythonbible
Version: 0.15.5
Author: Nathan Patton
Author-email: Nathan Patton <npatton@gmail.com>
License-Expression: MIT
Classifier: Intended Audience :: Information Technology
Classifier: Intended Audience :: Developers
Classifier: Operating System :: OS Independent
Classifier: Topic :: Software Development :: Libraries :: Python Modules
Classifier: Topic :: Software Development :: Libraries
Classifier: Topic :: Software Development
Classifier: Programming Language :: Python
Classifier: Programming Language :: Python :: 3
Classifier: Programming Language :: Python :: 3 :: Only
Classifier: Programming Language :: Python :: 3.10
Classifier: Programming Language :: Python :: 3.11
Classifier: Programming Language :: Python :: 3.12
Classifier: Programming Language :: Python :: 3.13
Classifier: Programming Language :: Python :: 3.14
Classifier: License :: OSI Approved :: MIT License
Requires-Dist: pythonbible-asv
Requires-Dist: pythonbible-akjv ; extra == 'akjv'
Requires-Dist: pythonbible-akjv ; extra == 'all'
Requires-Dist: pythonbible-asv ; extra == 'all'
Requires-Dist: pythonbible-bbe ; extra == 'all'
Requires-Dist: pythonbible-bwe ; extra == 'all'
Requires-Dist: pythonbible-dar ; extra == 'all'
Requires-Dist: pythonbible-diaglot ; extra == 'all'
Requires-Dist: pythonbible-dr ; extra == 'all'
Requires-Dist: pythonbible-etheridge ; extra == 'all'
Requires-Dist: pythonbible-gb ; extra == 'all'
Requires-Dist: pythonbible-kjv ; extra == 'all'
Requires-Dist: pythonbible-leeser ; extra == 'all'
Requires-Dist: pythonbible-lont ; extra == 'all'
Requires-Dist: pythonbible-mkjv1963 ; extra == 'all'
Requires-Dist: pythonbible-mont ; extra == 'all'
Requires-Dist: pythonbible-nheb ; extra == 'all'
Requires-Dist: pythonbible-oeb ; extra == 'all'
Requires-Dist: pythonbible-roth ; extra == 'all'
Requires-Dist: pythonbible-rwebster ; extra == 'all'
Requires-Dist: pythonbible-rylt ; extra == 'all'
Requires-Dist: pythonbible-tyn ; extra == 'all'
Requires-Dist: pythonbible-ukjv ; extra == 'all'
Requires-Dist: pythonbible-wbs ; extra == 'all'
Requires-Dist: pythonbible-web ; extra == 'all'
Requires-Dist: pythonbible-wesley ; extra == 'all'
Requires-Dist: pythonbible-wmth ; extra == 'all'
Requires-Dist: pythonbible-wyc ; extra == 'all'
Requires-Dist: pythonbible-ylt ; extra == 'all'
Requires-Dist: pythonbible-asv ; extra == 'asv'
Requires-Dist: pythonbible-bbe ; extra == 'bbe'
Requires-Dist: pythonbible-bwe ; extra == 'bwe'
Requires-Dist: pythonbible-dar ; extra == 'dar'
Requires-Dist: pythonbible-diaglot ; extra == 'diaglot'
Requires-Dist: pythonbible-dr ; extra == 'dr'
Requires-Dist: pythonbible-etheridge ; extra == 'etheridge'
Requires-Dist: pythonbible-gb ; extra == 'gb'
Requires-Dist: pythonbible-kjv ; extra == 'kjv'
Requires-Dist: pythonbible-leeser ; extra == 'leeser'
Requires-Dist: pythonbible-lont ; extra == 'lont'
Requires-Dist: pythonbible-mkjv1963 ; extra == 'mkjv1963'
Requires-Dist: pythonbible-mont ; extra == 'mont'
Requires-Dist: pythonbible-nheb ; extra == 'nheb'
Requires-Dist: pythonbible-oeb ; extra == 'oeb'
Requires-Dist: pythonbible-roth ; extra == 'roth'
Requires-Dist: pythonbible-rwebster ; extra == 'rwebster'
Requires-Dist: pythonbible-rylt ; extra == 'rylt'
Requires-Dist: pythonbible-tyn ; extra == 'tyn'
Requires-Dist: pythonbible-ukjv ; extra == 'ukjv'
Requires-Dist: pythonbible-wbs ; extra == 'wbs'
Requires-Dist: pythonbible-web ; extra == 'web'
Requires-Dist: pythonbible-wesley ; extra == 'wesley'
Requires-Dist: pythonbible-wmth ; extra == 'wmth'
Requires-Dist: pythonbible-wyc ; extra == 'wyc'
Requires-Dist: pythonbible-ylt ; extra == 'ylt'
Requires-Python: >=3.10
Project-URL: Documentation, https://docs.python.bible
Project-URL: Source, https://github.com/avendesora/pythonbible
Provides-Extra: akjv
Provides-Extra: all
Provides-Extra: asv
Provides-Extra: bbe
Provides-Extra: bwe
Provides-Extra: dar
Provides-Extra: diaglot
Provides-Extra: dr
Provides-Extra: etheridge
Provides-Extra: gb
Provides-Extra: kjv
Provides-Extra: leeser
Provides-Extra: lont
Provides-Extra: mkjv1963
Provides-Extra: mont
Provides-Extra: nheb
Provides-Extra: oeb
Provides-Extra: roth
Provides-Extra: rwebster
Provides-Extra: rylt
Provides-Extra: tyn
Provides-Extra: ukjv
Provides-Extra: wbs
Provides-Extra: web
Provides-Extra: wesley
Provides-Extra: wmth
Provides-Extra: wyc
Provides-Extra: ylt
